dynbps/BPS.py
dynbps/__init__.py
dynbps/_modidx.py
dynbps/loadData.py
dynbps/datasets/data.xlsx
dynbps-0.0.15.dist-info/LICENSE
dynbps-0.0.15.dist-info/METADATA
dynbps-0.0.15.dist-info/WHEEL
dynbps-0.0.15.dist-info/entry_points.txt
dynbps-0.0.15.dist-info/top_level.txt
dynbps-0.0.15.dist-info/RECORD
